{
  "mdmAccountId": "MDM-8521825691",
  "sfAccountId": "0015g00000WM5LD8L",
  "sapAccountId": "8521825691",
  "industrySector": "Healthcare",
  "businessRoles": [
    "soldto",
    "pickup",
    "billto"
  ],
  "legalForm": "GmbH",
  "name1": "Unilever Deutschland",
  "name2": null,
  "searchTerm": "Unilever",
  "language": "de",
  "currency": "EUR",
  "paymentTerms": "14 DAYS",
  "accountStatement": "WEEKLY",
  "creditLimit": 133066.25,
  "creditCurrency": "EUR",
  "isNaturalPerson": false,
  "primaryContactPersonId": "CONTACT-UD-852182",
  "primaryAddressId": "ADDRESS-UD-852182",
  "parentAccountId": null,
  "hasOrderBlock": true,
  "hasBillingBlock": false,
  "isTsaApproved": false,
  "customerType": "B2C",
  "salesPic": "hans.meyer@dhl.com",
  "salesManager": "Hans Meyer",
  "segmentGroup": "Retail",
  "segmentGroup2": "Industrial",
  "isTrustedCustomer": false,
  "ppdProfile": "PPD-DE-01",
  "avgPpdProfile": "PPD-EU-02",
  "isFirstTimeBuyer": true,
  "firstTimeBuyerDate": null
}